pybotnet/__init__.py
pybotnet/__main__.py
pybotnet/botnet.py
pybotnet/context.py
pybotnet/exceptions.py
pybotnet/package_info.py
pybotnet/engines/__init__.py
pybotnet/engines/base_engine.py
pybotnet/engines/telegram_engine.py
pybotnet/engines/test_engine.py
pybotnet/scripts/__init__.py
pybotnet/scripts/dos.py
pybotnet/scripts/echo.py
pybotnet/scripts/get_file.py
pybotnet/scripts/keylogger.py
pybotnet/scripts/openurl.py
pybotnet/scripts/put_file.py
pybotnet/scripts/reverse_shell.py
pybotnet/scripts/runcode.py
pybotnet/scripts/scheduler.py
pybotnet/scripts/screenshot.py
pybotnet/scripts/who.py
pybotnet/utils/__init__.py
pybotnet/utils/proxy.py
pybotnet/utils/serializer.py
pybotnet/utils/upload_server.py
pybotnet/utils/utils.py
pybotnet/utils/third_party_proxy/__init__.py
pybotnet/utils/third_party_proxy/httpdebugger.py
pybotnet/utils/third_party_proxy/reqbin.py
pybotnet-2.2.5.dist-info/LICENSE
pybotnet-2.2.5.dist-info/METADATA
pybotnet-2.2.5.dist-info/WHEEL
pybotnet-2.2.5.dist-info/top_level.txt
pybotnet-2.2.5.dist-info/RECORD
