Metadata-Version: 2.1
Name: pybotnet
Version: 2.2.5
Summary: A Python framework for building remote control, botnet , trojan or backdoor with Telegram or other control panels
Home-page: https://github.com/onionj/pybotnet
Author: onionj
Author-email: onionj98@gmail.com
License: gpl-3.0
Keywords: onionj pybotnet,python remote control,python backdoor,python botnet,pybotnet,python ddos,python backdoor,python trojan,reverse shell,python keyloggerframework
Classifier: License :: OSI Approved :: GNU Lesser General Public License v3 or later (LGPLv3+)
Classifier: Programming Language :: Python :: 3.8
Classifier: Programming Language :: Python :: 3.9
Requires-Python: >=3.8.0
License-File: LICENSE
Requires-Dist: beautifulsoup4 ==4.11.1
Requires-Dist: pillow ==10.2.0
Requires-Dist: pynput ==1.6.8
Requires-Dist: requests ==2.31.0
Requires-Dist: schedule ==1.1.0
